talos_linux_api/v1_2_0/__init__.py
talos_linux_api/v1_2_0/cluster/__init__.py
talos_linux_api/v1_2_0/common/__init__.py
talos_linux_api/v1_2_0/google/__init__.py
talos_linux_api/v1_2_0/google/rpc/__init__.py
talos_linux_api/v1_2_0/inspect/__init__.py
talos_linux_api/v1_2_0/machine/__init__.py
talos_linux_api/v1_2_0/resource/__init__.py
talos_linux_api/v1_2_0/resource/config/__init__.py
talos_linux_api/v1_2_0/resource/network/__init__.py
talos_linux_api/v1_2_0/securityapi/__init__.py
talos_linux_api/v1_2_0/storage/__init__.py
talos_linux_api/v1_2_0/time/__init__.py
talos_linux_api_v1.2.0-0.1.0.dist-info/WHEEL
talos_linux_api_v1.2.0-0.1.0.dist-info/METADATA
talos_linux_api_v1.2.0-0.1.0.dist-info/licenses/LICENSE
talos_linux_api_v1.2.0-0.1.0.dist-info/RECORD
